hat/gui/server/ui/script/snabbdom/helpers/attachto.js.map
hat/gui/server/ui/script/@hat-open/util/curry.d.ts
hat/gui/server/ui/script/snabbdom/modules/module.js.map
hat/gui/server/ui/script/snabbdom/modules/style.d.ts
hat/gui/server/ui/style/fonts/fontawesome.css
hat/gui/server/ui/script/snabbdom/modules/class.js.map
hat/gui/server/adapter.py
hat/gui/server/ui/script/snabbdom/h.js.map
hat/gui/server/ui/fonts/RobotoMono/RobotoMono.woff2
hat/gui/server/ui/script/snabbdom/tovnode.d.ts
hat/gui/server/ui/script/snabbdom/tovnode.js.map
hat/gui/server/ui/script/snabbdom/index.js.map
hat/gui/server/ui/script/@hat-open/juggler/package.json
hat/gui/server/ui/script/snabbdom/modules/props.js
hat/gui/server/ui/script/snabbdom/init.js.map
hat/gui/server/ui/fonts/Inter/Inter.woff2
hat/gui/server/ui/script/snabbdom/thunk.js
hat/gui/server/ui/script/main.js
hat/gui/server/ui/script/@hat-open/renderer/index.js
hat/gui/server/ui/fonts/FontAwesome/FontAwesome.woff2
hat/gui/server/ui/script/snabbdom/is.js
hat/gui/server/ui/script/snabbdom/htmldomapi.d.ts
hat/gui/server/ui/script/@hat-open/util/patch.d.ts
hat/gui/server/ui/script/@hat-open/util/package.json
hat/gui/server/ui/script/snabbdom/modules/module.js
hat/gui/server/ui/script/snabbdom/modules/attributes.js
hat/gui/server/ui/script/@hat-open/util/promise.js
hat/gui/server/ui/script/@hat-open/util/timestamp.d.ts
hat/gui/server/ui/script/snabbdom/index.d.ts
hat/gui/server/ui/script/snabbdom/is.js.map
hat/gui/server/ui/script/snabbdom/vnode.js
hat/gui/server/view.py
hat/gui/server/ui/script/@hat-open/util/iter.js
hat/gui/server/ui/script/snabbdom/init.d.ts
hat/gui/server/ui/script/@hat-open/util/iter.d.ts
hat/gui/passwd.py
hat/gui/server/ui/script/@hat-open/renderer/package.json
hat/gui/server/ui/script/snabbdom/jsx.js.map
hat/gui/server/ui/script/@hat-open/juggler/README.md
hat/gui/server/ui/script/snabbdom/hooks.js.map
hat/gui/server/ui/script/@hat-open/util/misc.d.ts
hat/gui/__init__.py
hat_gui-0.7.13.dist-info/LICENSE
hat_gui-0.7.13.dist-info/entry_points.txt
hat_gui-0.7.13.dist-info/METADATA
hat_gui-0.7.13.dist-info/WHEEL
hat_gui-0.7.13.dist-info/RECORD
